[
    {
        "account": "wqobq.wam",
        "nonce": null
    },
    {
        "account": "p4qbs.wam",
        "nonce": null
    },
    {
        "account": "xlit2.wam",
        "nonce": null
    },
    {
        "account": "npld2.wam",
        "nonce": null
    },
    {
        "account": "g1md2.wam",
        "nonce": null
    },
    {
        "account": "tpud2.wam",
        "nonce": null
    },
    {
        "account": "xxvd2.wam",
        "nonce": null
    },
    {
        "account": "wjqt2.wam",
        "nonce": null
    },
    {
        "account": "xnqt2.wam",
        "nonce": null
    },
    {
        "account": "yjqt2.wam",
        "nonce": null
    },
    {
        "account": "ozudm.wam",
        "nonce": null
    },
    {
        "account": "zrutm.wam",
        "nonce": null
    },
    {
        "account": "yfvdm.wam",
        "nonce": null
    },
    {
        "account": "h3vtm.wam",
        "nonce": null
    },
    {
        "account": "vvvtm.wam",
        "nonce": null
    },
    {
        "account": "4rztm.wam",
        "nonce": null
    },
    {
        "account": "mjztm.wam",
        "nonce": null
    },
    {
        "account": "qg.do..wam",
        "nonce": null
    },
    {
        "account": "lo.to.wam",
        "nonce": null
    },
    {
        "account": "js1do.wam",
        "nonce": null
    }
]